bibliotheca_client/__init__.py
bibliotheca_client/client.py
bibliotheca_client-0.1.0.dist-info/METADATA
bibliotheca_client-0.1.0.dist-info/WHEEL
bibliotheca_client-0.1.0.dist-info/top_level.txt
bibliotheca_client-0.1.0.dist-info/RECORD
