Metadata-Version: 2.4
Name: bibliotheca-client
Version: 0.1.0
Summary: Python client library for Bibliotheca data exploration platform
Home-page: https://pantology.io/anthology
Author: Pantology Team
Author-email: Pantology Team <hi@pantology.io>
License: Apache-2.0
Project-URL: Homepage, https://pantology.io/anthology
Project-URL: Documentation, https://pantology.io/anthology
Classifier: Development Status :: 3 - Alpha
Classifier: Intended Audience :: Developers
Classifier: Topic :: Software Development :: Libraries :: Python Modules
Classifier: License :: OSI Approved :: Apache Software License
Classifier: Programming Language :: Python :: 3
Classifier: Programming Language :: Python :: 3.8
Classifier: Programming Language :: Python :: 3.9
Classifier: Programming Language :: Python :: 3.10
Classifier: Programming Language :: Python :: 3.11
Classifier: Programming Language :: Python :: 3.12
Requires-Python: >=3.8
Requires-Dist: requests>=2.28.0
Requires-Dist: pandas>=1.5.0
Requires-Dist: sqlglot>=20.0.0
Provides-Extra: dev
Requires-Dist: pytest>=7.0.0; extra == "dev"
Requires-Dist: black>=22.0.0; extra == "dev"
Requires-Dist: mypy>=0.990; extra == "dev"
Dynamic: author
Dynamic: home-page
Dynamic: requires-python
